pybullet_robot/__init__.py
pybullet_robot/bullet_robot.py
pybullet_robot/pybullet_ik_interface.py
pybullet_robot/utils/__init__.py
pybullet_robot/utils/robot_loader_utils.py
pybullet_robot-0.1.4.dist-info/METADATA
pybullet_robot-0.1.4.dist-info/WHEEL
pybullet_robot-0.1.4.dist-info/top_level.txt
pybullet_robot-0.1.4.dist-info/RECORD
