Metadata-Version: 2.1
Name: pybullet_robot
Version: 0.1.4
Summary: A generel Python interface class for robot simulations using PyBullet. Also provides an IK interface for multi-end-effector robots that uses bullet physics as a solver.
Author-email: Saif Sidhik <mail@saifsidhik.page>
Requires-Python: >=3.10
Requires-Dist: robot-descriptions <2,>=1.11.0
Requires-Dist: numpy <3,>=1.6
Requires-Dist: scipy <2,>=1.14.0
Requires-Dist: pybullet <4,>=3.2.6
